MANIFEST.in
setup.py
src/twitter/__init__.py
src/twitter.checkstyle.egg-info/PKG-INFO
src/twitter.checkstyle.egg-info/SOURCES.txt
src/twitter.checkstyle.egg-info/dependency_links.txt
src/twitter.checkstyle.egg-info/entry_points.txt
src/twitter.checkstyle.egg-info/namespace_packages.txt
src/twitter.checkstyle.egg-info/requires.txt
src/twitter.checkstyle.egg-info/top_level.txt
src/twitter.checkstyle.egg-info/zip-safe
src/twitter/checkstyle/__init__.py
src/twitter/checkstyle/checker.py
src/twitter/checkstyle/common.py
src/twitter/checkstyle/iterators.py
src/twitter/checkstyle/plugins/__init__.py
src/twitter/checkstyle/plugins/class_factoring.py
src/twitter/checkstyle/plugins/except_statements.py
src/twitter/checkstyle/plugins/future_compatibility.py
src/twitter/checkstyle/plugins/import_order.py
src/twitter/checkstyle/plugins/indentation.py
src/twitter/checkstyle/plugins/missing_contextmanager.py
src/twitter/checkstyle/plugins/new_style_classes.py
src/twitter/checkstyle/plugins/newlines.py
src/twitter/checkstyle/plugins/pep8.py
src/twitter/checkstyle/plugins/print_statements.py
src/twitter/checkstyle/plugins/pyflakes.py
src/twitter/checkstyle/plugins/trailing_whitespace.py
src/twitter/checkstyle/plugins/variable_names.py