Metadata-Version: 1.0
Name: twitter.checkstyle
Version: 0.1.0
Summary: Twitter's python styleguide checkstyle tool.
Home-page: https://github.com/twitter/commons/tree/master/src/python/twitter/checkstyle
Author: UNKNOWN
Author-email: UNKNOWN
License: Apache License, Version 2.0
Platform: UNKNOWN
